certbot_deployer_ssh/__init__.py
certbot_deployer_ssh/__main__.py
certbot_deployer_ssh/meta.py
certbot_deployer_ssh/_main/__init__.py
certbot_deployer_ssh/certbot_deployer_ssh/__init__.py
certbot_deployer_ssh-1.0.0.dist-info/licenses/LICENSE
certbot_deployer_ssh-1.0.0.dist-info/METADATA
certbot_deployer_ssh-1.0.0.dist-info/WHEEL
certbot_deployer_ssh-1.0.0.dist-info/entry_points.txt
certbot_deployer_ssh-1.0.0.dist-info/top_level.txt
certbot_deployer_ssh-1.0.0.dist-info/RECORD
