Metadata-Version: 2.4
Name: certbot_deployer_ssh
Version: 1.0.0
Summary: Certbot Deployer plugin for deploying certificate bundles over SSH
Home-page: https://github.com/theias/certbot_deployer_ssh
Author: IAS
Author-email: network@ias.edu
Project-URL: Documentation, https://theias.github.io/certbot_deployer_ssh/
Project-URL: Bug Tracker, https://github.com/theias/certbot_deployer_ssh/issues
Project-URL: Source, https://github.com/theias/certbot_deployer_ssh
Classifier: Programming Language :: Python :: 3
Classifier: License :: OSI Approved :: MIT License
Classifier: Operating System :: OS Independent
Requires-Python: >=3.9
License-File: LICENSE
Requires-Dist: certbot_deployer<3.0.0,>=2.0.3
Requires-Dist: cryptography<45.0.0,>=44.0.1
Requires-Dist: fabric<4.0.0,>=3.2.2
Dynamic: license-file
